hw3/hw3.v
// Homework 3
// Fall 2019
// set PATH=%PATH%;C:\iverilog\bin

module BitCounter(Count,ClearCounter,IncCounter,clk,reset);
	output[7:0] Count;
	input		ClearCounter, IncCounter;
	input		clk, reset;
	reg	[7:0] 	Count, nCount;
	
	always @ (posedge clk) begin
		if (reset) assign Count = 8'b0000_0000;
		else Count <= nCount;
	end
		
	always @ (negedge clk) begin
		if (ClearCounter) nCount <= 8'b0000_0000;
		else if(IncCounter) nCount <= Count + 1;
		else nCount <= Count;		
	end
	
endmodule

module ShiftRegister(CurrentBit,sw,LoadRegister,RotateRegisterLeft,clk,reset);
	output			CurrentBit;
	input	[15:4] 	sw;
	input			LoadRegister, RotateRegisterLeft;
	input			clk, reset;
	
	parameter		DEFAULTREG = 24'h0F0F0F;
	
	reg		[23:0]  TheReg, nTheReg;

	always @ (posedge clk) begin
		if(reset) TheReg <= DEFAULTREG;
		else TheReg <= nTheReg;
	end
	
	always @ (negedge clk) begin
		if(LoadRegister)begin
			nTheReg <= {sw[15:12], 4'b0000, sw[11:8], 4'b0000, sw[7:4], 4'b0000};
		end
		else if(RotateRegisterLeft)begin
			nTheReg <= {nTheReg[22:0], nTheReg[23]};
		end
		else nTheReg <= nTheReg;
	end
	
	assign CurrentBit = TheReg[23];
	
endmodule

module Hex27Seg(Leds,HexVal);
	output	[0:6] 	Leds;
	input	[3:0] 	HexVal;
	reg		[0:6] 	Leds;
	
	always @(HexVal) begin
		case(HexVal)
			4'h0:  Leds = 7'b000_0001;
            4'h1:  Leds = 7'b100_1111;
            4'h2:  Leds = 7'b001_0010;
            4'h3:  Leds = 7'b000_0110;
            4'h4:  Leds = 7'b100_1100;
            4'h5:  Leds = 7'b010_0100;
            4'h6:  Leds = 7'b010_0000;
            4'h7:  Leds = 7'b000_1111;
            4'h8:  Leds = 7'b000_0000;
            4'h9:  Leds = 7'b000_0100;
            4'hF:  Leds = 7'b111_1111;
            default:  Leds = 7'b000_0001;
		endcase
	end
	
endmodule

hw3/hw3_tb_3.v
// Homework 3 testbench 3
// Fall 2018
// set PATH=%PATH%;C:\iverilog\bin

`timescale 1ns / 1ps
module tbHex27Seg;
	wire	[0:6] 	tLeds;
	reg		[3:0] 	tHexVal;
	
	Hex27Seg	tb(tLeds,tHexVal);
	
	initial begin #100 $finish; end
	initial begin
		$dumpfile("hw3-3.vcd");
		$dumpvars(0,tbHex27Seg);
	end
	
	initial begin
	tHexVal = 4'b0000;
	while (tHexVal < 15)
	#5 tHexVal = tHexVal + 1;
	end
	
endmodule

hw3/hw3-3.vcd
$date
	Mon Sep 23 21:36:00 2019
$end
$version
	Icarus Verilog
$end
$timescale
	1ps
$end
$scope module tbHex27Seg $end
$var wire 7 ! tLeds [0:6] $end
$var reg 4 " tHexVal [3:0] $end
$scope module tb $end
$var wire 4 # HexVal [3:0] $end
$var reg 7 $ Leds [0:6] $end
$upscope $end
$upscope $end
$enddefinitions $end
#0
$dumpvars
b1 $
b0 #
b0 "
b1 !
$end
#5000
b1001111 !
b1001111 $
b1 "
b1 #
#10000
b10010 !
b10010 $
b10 "
b10 #
#15000
b110 !
b110 $
b11 "
b11 #
#20000
b1001100 !
b1001100 $
b100 "
b100 #
#25000
b100100 !
b100100 $
b101 "
b101 #
#30000
b100000 !
b100000 $
b110 "
b110 #
#35000
b1111 !
b1111 $
b111 "
b111 #
#40000
b0 !
b0 $
b1000 "
b1000 #
#45000
b100 !
b100 $
b1001 "
b1001 #
#50000
b1 !
b1 $
b1010 "
b1010 #
#55000
b1011 "
b1011 #
#60000
b1100 "
b1100 #
#65000
b1101 "
b1101 #
#70000
b1110 "
b1110 #
#75000
b1111111 !
b1111111 $
b1111 "
b1111 #
