hw3/hw3.v
// Homework 3
// Fall 2019
// set PATH=%PATH%;C:\iverilog\bin

module BitCounter(Count,ClearCounter,IncCounter,clk,reset);
	output[7:0] Count;
	input		ClearCounter, IncCounter;
	input		clk, reset;
	reg	[7:0] 	Count, nCount;
	
	always @ (posedge clk) begin
		if (reset) assign Count = 8'b0000_0000;
		else Count <= nCount;
	end
		
	always @ (negedge clk) begin
		if (ClearCounter) nCount <= 8'b0000_0000;
		else if(IncCounter) nCount <= Count + 1;
		else nCount <= Count;		
	end
	
endmodule

module ShiftRegister(CurrentBit,sw,LoadRegister,RotateRegisterLeft,clk,reset);
	output			CurrentBit;
	input	[15:4] 	sw;
	input			LoadRegister, RotateRegisterLeft;
	input			clk, reset;
	
	parameter		DEFAULTREG = 24'h0F0F0F;
	
	reg		[23:0]  TheReg, nTheReg;

	always @ (posedge clk) begin
		if(reset) TheReg <= DEFAULTREG;
		else TheReg <= nTheReg;
	end
	
	always @ (negedge clk) begin
		if(LoadRegister)begin
			nTheReg <= {sw[15:12], 4'b0000, sw[11:8], 4'b0000, sw[7:4], 4'b0000};
		end
		else if(RotateRegisterLeft)begin
			nTheReg <= {nTheReg[22:0], nTheReg[23]};
		end
		else nTheReg <= nTheReg;
	end
	
	assign CurrentBit = TheReg[23];
	
endmodule

module Hex27Seg(Leds,HexVal);
	output	[0:6] 	Leds;
	input	[3:0] 	HexVal;
	reg		[0:6] 	Leds;
	
	always @(HexVal) begin
		case(HexVal)
			4'h0:  Leds = 7'b000_0001;
            4'h1:  Leds = 7'b100_1111;
            4'h2:  Leds = 7'b001_0010;
            4'h3:  Leds = 7'b000_0110;
            4'h4:  Leds = 7'b100_1100;
            4'h5:  Leds = 7'b010_0100;
            4'h6:  Leds = 7'b010_0000;
            4'h7:  Leds = 7'b000_1111;
            4'h8:  Leds = 7'b000_0000;
            4'h9:  Leds = 7'b000_0100;
            4'hF:  Leds = 7'b111_1111;
            default:  Leds = 7'b000_0001;
		endcase
	end
	
endmodule

hw3/hw3_tb_1.v
// Homework 3 testbench 1
// Fall 2018
// set PATH=%PATH%;C:\iverilog\bin

`timescale 1ns / 1ps
module tbBitCounter;
	wire	[7:0] 	tCount;
	reg				tClearCounter, tIncCounter;
	reg				tclk, treset;
	
	BitCounter	tb(tCount,tClearCounter,tIncCounter,tclk,treset);
	
	initial #1000 $finish;
	initial begin tclk = 0; forever #5 tclk = ~tclk; end
	initial begin
		$dumpfile("hw3-1.vcd");
		$dumpvars(0,tbBitCounter);
	end
	
	initial begin
	tClearCounter = 1;
	tIncCounter = 1;
	treset = 0;
	#10 tClearCounter = 0;
	#100 tIncCounter = 1;
	#500 tClearCounter = 1;
	#100 tClearCounter = 0;
	#200 treset = 1;
	end
	
endmodule

hw3/hw3-1.vcd
$date
	Mon Sep 23 21:04:28 2019
$end
$version
	Icarus Verilog
$end
$timescale
	1ps
$end
$scope module tbBitCounter $end
$var wire 8 ! tCount [7:0] $end
$var reg 1 " tClearCounter $end
$var reg 1 # tIncCounter $end
$var reg 1 $ tclk $end
$var reg 1 % treset $end
$scope module tb $end
$var wire 1 " ClearCounter $end
$var wire 1 # IncCounter $end
$var wire 1 $ clk $end
$var wire 1 % reset $end
$var reg 8 & Count [7:0] $end
$var reg 8 ' nCount [7:0] $end
$upscope $end
$upscope $end
$enddefinitions $end
#0
$dumpvars
b0 '
bx &
0%
0$
1#
1"
bx !
$end
#5000
b0 !
b0 &
1$
#10000
b1 '
0$
0"
#15000
b1 !
b1 &
1$
#20000
b10 '
0$
#25000
b10 !
b10 &
1$
#30000
b11 '
0$
#35000
b11 !
b11 &
1$
#40000
b100 '
0$
#45000
b100 !
b100 &
1$
#50000
b101 '
0$
#55000
b101 !
b101 &
1$
#60000
b110 '
0$
#65000
b110 !
b110 &
1$
#70000
b111 '
0$
#75000
b111 !
b111 &
1$
#80000
b1000 '
0$
#85000
b1000 !
b1000 &
1$
#90000
b1001 '
0$
#95000
b1001 !
b1001 &
1$
#100000
b1010 '
0$
#105000
b1010 !
b1010 &
1$
#110000
b1011 '
0$
#115000
b1011 !
b1011 &
1$
#120000
b1100 '
0$
#125000
b1100 !
b1100 &
1$
#130000
b1101 '
0$
#135000
b1101 !
b1101 &
1$
#140000
b1110 '
0$
#145000
b1110 !
b1110 &
1$
#150000
b1111 '
0$
#155000
b1111 !
b1111 &
1$
#160000
b10000 '
0$
#165000
b10000 !
b10000 &
1$
#170000
b10001 '
0$
#175000
b10001 !
b10001 &
1$
#180000
b10010 '
0$
#185000
b10010 !
b10010 &
1$
#190000
b10011 '
0$
#195000
b10011 !
b10011 &
1$
#200000
b10100 '
0$
#205000
b10100 !
b10100 &
1$
#210000
b10101 '
0$
#215000
b10101 !
b10101 &
1$
#220000
b10110 '
0$
#225000
b10110 !
b10110 &
1$
#230000
b10111 '
0$
#235000
b10111 !
b10111 &
1$
#240000
b11000 '
0$
#245000
b11000 !
b11000 &
1$
#250000
b11001 '
0$
#255000
b11001 !
b11001 &
1$
#260000
b11010 '
0$
#265000
b11010 !
b11010 &
1$
#270000
b11011 '
0$
#275000
b11011 !
b11011 &
1$
#280000
b11100 '
0$
#285000
b11100 !
b11100 &
1$
#290000
b11101 '
0$
#295000
b11101 !
b11101 &
1$
#300000
b11110 '
0$
#305000
b11110 !
b11110 &
1$
#310000
b11111 '
0$
#315000
b11111 !
b11111 &
1$
#320000
b100000 '
0$
#325000
b100000 !
b100000 &
1$
#330000
b100001 '
0$
#335000
b100001 !
b100001 &
1$
#340000
b100010 '
0$
#345000
b100010 !
b100010 &
1$
#350000
b100011 '
0$
#355000
b100011 !
b100011 &
1$
#360000
b100100 '
0$
#365000
b100100 !
b100100 &
1$
#370000
b100101 '
0$
#375000
b100101 !
b100101 &
1$
#380000
b100110 '
0$
#385000
b100110 !
b100110 &
1$
#390000
b100111 '
0$
#395000
b100111 !
b100111 &
1$
#400000
b101000 '
0$
#405000
b101000 !
b101000 &
1$
#410000
b101001 '
0$
#415000
b101001 !
b101001 &
1$
#420000
b101010 '
0$
#425000
b101010 !
b101010 &
1$
#430000
b101011 '
0$
#435000
b101011 !
b101011 &
1$
#440000
b101100 '
0$
#445000
b101100 !
b101100 &
1$
#450000
b101101 '
0$
#455000
b101101 !
b101101 &
1$
#460000
b101110 '
0$
#465000
b101110 !
b101110 &
1$
#470000
b101111 '
0$
#475000
b101111 !
b101111 &
1$
#480000
b110000 '
0$
#485000
b110000 !
b110000 &
1$
#490000
b110001 '
0$
#495000
b110001 !
b110001 &
1$
#500000
b110010 '
0$
#505000
b110010 !
b110010 &
1$
#510000
b110011 '
0$
#515000
b110011 !
b110011 &
1$
#520000
b110100 '
0$
#525000
b110100 !
b110100 &
1$
#530000
b110101 '
0$
#535000
b110101 !
b110101 &
1$
#540000
b110110 '
0$
#545000
b110110 !
b110110 &
1$
#550000
b110111 '
0$
#555000
b110111 !
b110111 &
1$
#560000
b111000 '
0$
#565000
b111000 !
b111000 &
1$
#570000
b111001 '
0$
#575000
b111001 !
b111001 &
1$
#580000
b111010 '
0$
#585000
b111010 !
b111010 &
1$
#590000
b111011 '
0$
#595000
b111011 !
b111011 &
1$
#600000
b111100 '
0$
#605000
b111100 !
b111100 &
1$
#610000
b0 '
0$
1"
#615000
b0 !
b0 &
1$
#620000
0$
#625000
1$
#630000
0$
#635000
1$
#640000
0$
#645000
1$
#650000
0$
#655000
1$
#660000
0$
#665000
1$
#670000
0$
#675000
1$
#680000
0$
#685000
1$
#690000
0$
#695000
1$
#700000
0$
#705000
1$
#710000
b1 '
0$
0"
#715000
b1 !
b1 &
1$
#720000
b10 '
0$
#725000
b10 !
b10 &
1$
#730000
b11 '
0$
#735000
b11 !
b11 &
1$
#740000
b100 '
0$
#745000
b100 !
b100 &
1$
#750000
b101 '
0$
#755000
b101 !
b101 &
1$
#760000
b110 '
0$
#765000
b110 !
b110 &
1$
#770000
b111 '
0$
#775000
b111 !
b111 &
1$
#780000
b1000 '
0$
#785000
b1000 !
b1000 &
1$
#790000
b1001 '
0$
#795000
b1001 !
b1001 &
1$
#800000
b1010 '
0$
#805000
b1010 !
b1010 &
1$
#810000
b1011 '
0$
#815000
b1011 !
b1011 &
1$
#820000
b1100 '
0$
#825000
b1100 !
b1100 &
1$
#830000
b1101 '
0$
#835000
b1101 !
b1101 &
1$
#840000
b1110 '
0$
#845000
b1110 !
b1110 &
1$
#850000
b1111 '
0$
#855000
b1111 !
b1111 &
1$
#860000
b10000 '
0$
#865000
b10000 !
b10000 &
1$
#870000
b10001 '
0$
#875000
b10001 !
b10001 &
1$
#880000
b10010 '
0$
#885000
b10010 !
b10010 &
1$
#890000
b10011 '
0$
#895000
b10011 !
b10011 &
1$
#900000
b10100 '
0$
#905000
b10100 !
b10100 &
1$
#910000
b10101 '
0$
1%
#915000
b0 !
b0 &
1$
#920000
b1 '
0$
