hw3/hw3.v
// Homework 3
// Fall 2019
// set PATH=%PATH%;C:\iverilog\bin

module BitCounter(Count,ClearCounter,IncCounter,clk,reset);
	output[7:0] Count;
	input		ClearCounter, IncCounter;
	input		clk, reset;
	reg	[7:0] 	Count, nCount;
	
	always @ (posedge clk) begin
		if (reset) assign Count = 8'b0000_0000;
		else Count <= nCount;
	end
		
	always @ (negedge clk) begin
		if (ClearCounter) nCount <= 8'b0000_0000;
		else if(IncCounter) nCount <= Count + 1;
		else nCount <= Count;		
	end
	
endmodule

module ShiftRegister(CurrentBit,sw,LoadRegister,RotateRegisterLeft,clk,reset);
	output			CurrentBit;
	input	[15:4] 	sw;
	input			LoadRegister, RotateRegisterLeft;
	input			clk, reset;
	
	parameter		DEFAULTREG = 24'h0F0F0F;
	
	reg		[23:0]  TheReg, nTheReg;

	always @ (posedge clk) begin
		if(reset) TheReg <= DEFAULTREG;
		else TheReg <= nTheReg;
	end
	
	always @ (negedge clk) begin
		if(LoadRegister)begin
			nTheReg <= {sw[15:12], 4'b0000, sw[11:8], 4'b0000, sw[7:4], 4'b0000};
		end
		else if(RotateRegisterLeft)begin
			nTheReg <= {nTheReg[22:0], nTheReg[23]};
		end
		else nTheReg <= nTheReg;
	end
	
	assign CurrentBit = TheReg[23];
	
endmodule

module Hex27Seg(Leds,HexVal);
	output	[0:6] 	Leds;
	input	[3:0] 	HexVal;
	reg		[0:6] 	Leds;
	
	always @(HexVal) begin
		case(HexVal)
			4'h0:  Leds = 7'b000_0001;
            4'h1:  Leds = 7'b100_1111;
            4'h2:  Leds = 7'b001_0010;
            4'h3:  Leds = 7'b000_0110;
            4'h4:  Leds = 7'b100_1100;
            4'h5:  Leds = 7'b010_0100;
            4'h6:  Leds = 7'b010_0000;
            4'h7:  Leds = 7'b000_1111;
            4'h8:  Leds = 7'b000_0000;
            4'h9:  Leds = 7'b000_0100;
            4'hF:  Leds = 7'b111_1111;
            default:  Leds = 7'b000_0001;
		endcase
	end
	
endmodule

hw3/hw3_tb_2.v
// Homework 3 testbench 2
// Fall 2018
// C

`timescale 1ns / 1ps
module tbShiftRegister;
	wire			tCurrentBit;
	reg		[15:4] 	tsw;
	reg				tLoadRegister, tRotateRegisterLeft;
	reg				tclk, treset;
	
	ShiftRegister	tb(tCurrentBit,tsw,tLoadRegister,tRotateRegisterLeft,tclk,treset);
	
	initial #200 $finish;
	initial begin tclk = 0; forever #5 tclk = ~tclk; end
	initial begin
		$dumpfile("hw3-2.vcd");
		$dumpvars(0, tbShiftRegister);
	end
	
	initial begin
	tsw = 12'b000000000000;
	tLoadRegister = 1;
	treset = 0;
	#10	tLoadRegister = 0;
	#5	tRotateRegisterLeft = 1;
	#20	treset = 1;
	#10	treset = 0; tsw = 12'b111111111111;
	#10 tLoadRegister = 1;
	#10 tLoadRegister = 0;
	#10 tRotateRegisterLeft = 1;
	end
endmodule

hw3/hw3-2.vcd
$date
	Mon Sep 23 21:40:26 2019
$end
$version
	Icarus Verilog
$end
$timescale
	1ps
$end
$scope module tbShiftRegister $end
$var wire 1 ! tCurrentBit $end
$var reg 1 " tLoadRegister $end
$var reg 1 # tRotateRegisterLeft $end
$var reg 1 $ tclk $end
$var reg 1 % treset $end
$var reg 12 & tsw [15:4] $end
$scope module tb $end
$var wire 1 " LoadRegister $end
$var wire 1 # RotateRegisterLeft $end
$var wire 1 $ clk $end
$var wire 1 % reset $end
$var wire 12 ' sw [15:4] $end
$var wire 1 ! CurrentBit $end
$var reg 24 ( TheReg [23:0] $end
$var reg 24 ) nTheReg [23:0] $end
$upscope $end
$upscope $end
$enddefinitions $end
#0
$dumpvars
b0 )
bx (
b0 '
b0 &
0%
0$
x#
1"
x!
$end
#5000
0!
b0 (
1$
#10000
0$
0"
#15000
1$
1#
#20000
0$
#25000
1$
#30000
0$
#35000
b11110000111100001111 (
1$
1%
#40000
0$
#45000
b0 (
1$
b111111111111 &
b111111111111 '
0%
#50000
0$
#55000
1$
1"
#60000
b111100001111000011110000 )
0$
#65000
1!
b111100001111000011110000 (
1$
0"
#70000
b111000011110000111100001 )
0$
#75000
b111000011110000111100001 (
1$
#80000
b110000111100001111000011 )
0$
#85000
b110000111100001111000011 (
1$
#90000
b100001111000011110000111 )
0$
#95000
b100001111000011110000111 (
1$
#100000
b11110000111100001111 )
0$
#105000
0!
b11110000111100001111 (
1$
#110000
b111100001111000011110 )
0$
#115000
b111100001111000011110 (
1$
#120000
b1111000011110000111100 )
0$
#125000
b1111000011110000111100 (
1$
#130000
b11110000111100001111000 )
0$
#135000
b11110000111100001111000 (
1$
#140000
b111100001111000011110000 )
0$
#145000
1!
b111100001111000011110000 (
1$
#150000
b111000011110000111100001 )
0$
#155000
b111000011110000111100001 (
1$
#160000
b110000111100001111000011 )
0$
#165000
b110000111100001111000011 (
1$
#170000
b100001111000011110000111 )
0$
#175000
b100001111000011110000111 (
1$
#180000
b11110000111100001111 )
0$
#185000
0!
b11110000111100001111 (
1$
#190000
b111100001111000011110 )
0$
#195000
b111100001111000011110 (
1$
#200000
b1111000011110000111100 )
0$
